reggie/__init__.py
reggie/core.py
reggie/models.py
reggie/utils.py
reggie/checkers/__init__.py
reggie/checkers/base.py
reggie/checkers/nsw.py
reggie/checkers/qld.py
reggie/checkers/template_checker.py
arch_reggie-0.1.0.dist-info/METADATA
arch_reggie-0.1.0.dist-info/WHEEL
arch_reggie-0.1.0.dist-info/licenses/LICENSE
arch_reggie-0.1.0.dist-info/RECORD
