Metadata-Version: 2.4
Name: arch-reggie
Version: 0.1.0
Summary: A package for checking professional registration status across various certification bodies
Project-URL: Homepage, https://github.com/bvn-architecture/Reggie
Project-URL: Documentation, https://arch-reggie.readthedocs.io
Project-URL: Repository, https://github.com/bvn-architecture/Reggie
Project-URL: Issues, https://github.com/bvn-architecture/arch-reggie/issues
Author-email: Ben Doherty <ben_doherty@bvn.com.au>
License-Expression: MIT
License-File: LICENSE
Keywords: BVN,NSW,QLD,architecture,registration
Classifier: Development Status :: 4 - Beta
Classifier: Intended Audience :: Developers
Classifier: License :: OSI Approved :: MIT License
Classifier: Programming Language :: Python :: 3
Classifier: Programming Language :: Python :: 3.8
Classifier: Programming Language :: Python :: 3.9
Classifier: Programming Language :: Python :: 3.10
Classifier: Programming Language :: Python :: 3.11
Classifier: Programming Language :: Python :: 3.12
Requires-Python: >=3.8
Requires-Dist: beautifulsoup4>=4.9.0
Requires-Dist: pandas>=1.3.0
Requires-Dist: requests>=2.25.0
Requires-Dist: selenium>=4.0.0
Requires-Dist: webdriver-manager>=3.8.0
Provides-Extra: dev
Requires-Dist: black; extra == 'dev'
Requires-Dist: isort; extra == 'dev'
Requires-Dist: mypy; extra == 'dev'
Requires-Dist: pre-commit; extra == 'dev'
Requires-Dist: pytest-cov; extra == 'dev'
Requires-Dist: pytest>=6.0; extra == 'dev'
